<?xml version="1.0" encoding="UTF-8" ?>
<tv generator-info-name="Processed by Open-EPG Visual Processor v1.0" generator-info-url="https://www.open-epg.com">
<channel id="Canal Macau Ch. 92.mo"><display-name>Canal Macau Ch. 92.mo</display-name></channel>
<channel id="Ou Mun Tin Toi FM100.7.mo"><display-name>Ou Mun Tin Toi FM100.7.mo</display-name></channel>
<channel id="Ou Mun-Macau Ch.96.mo"><display-name>Ou Mun-Macau Ch.96.mo</display-name></channel>
<channel id="Rádio Macau FM98.mo"><display-name>Rádio Macau FM98.mo</display-name></channel>
<channel id="TDM Entertainment Ch.95.mo"><display-name>TDM Entertainment Ch.95.mo</display-name></channel>
<channel id="TDM Info Ch.94.mo"><display-name>TDM Info Ch.94.mo</display-name></channel>
<channel id="TDM Ou Mun Ch. 91.mo"><display-name>TDM Ou Mun Ch. 91.mo</display-name></channel>
<channel id="TDM Sport Ch.93.mo"><display-name>TDM Sport Ch.93.mo</display-name></channel>
<programme start="20251211052500 +0000" stop="20251211062500 +0000" channel="Canal Macau Ch. 92.mo"><title>News (RTPi) Delayed Broadcast</title></programme>
<programme start="20251211062500 +0000" stop="20251211070000 +0000" channel="Canal Macau Ch. 92.mo"><title>Chefs Friends S1</title></programme>
<programme start="20251211070000 +0000" stop="20251211074500 +0000" channel="Canal Macau Ch. 92.mo"><title>Executive Council Press Conference (Live)</title></programme>
<programme start="20251211074500 +0000" stop="20251211083500 +0000" channel="Canal Macau Ch. 92.mo"><title>A Herdeira S2</title></programme>
<programme start="20251211083500 +0000" stop="20251211084500 +0000" channel="Canal Macau Ch. 92.mo"><title>Pocoyo S1</title></programme>
<programme start="20251211084500 +0000" stop="20251211093500 +0000" channel="Canal Macau Ch. 92.mo"><title>Red Moon</title></programme>
<programme start="20251211093500 +0000" stop="20251211101500 +0000" channel="Canal Macau Ch. 92.mo"><title>Kallys Mashup</title></programme>
<programme start="20251211101500 +0000" stop="20251211111000 +0000" channel="Canal Macau Ch. 92.mo"><title>Did You Know?</title><desc>If you had to explain science to someone who does not know a thing about it, how would you do?You no longer have to ask yourself this question since DID YOU KNOW? is here for that! Every episode is explaining clearly and simply your daily environment: health and well-being, human body, animals, earth, home, food, technology…Monday to Friday at 6:30PM</desc></programme>
<programme start="20251211111000 +0000" stop="20251211120000 +0000" channel="Canal Macau Ch. 92.mo"><title>Cacau</title></programme>
<programme start="20251211120000 +0000" stop="20251211124000 +0000" channel="Canal Macau Ch. 92.mo"><title>Main News, Financial and Weather Report</title></programme>
<programme start="20251211124000 +0000" stop="20251211132000 +0000" channel="Canal Macau Ch. 92.mo"><title>TDM Entrevista - Carmen Amado Mendes</title></programme>
<programme start="20251211132000 +0000" stop="20251211134000 +0000" channel="Canal Macau Ch. 92.mo"><title>Into Water and Beyond</title><desc>Ben and Di embark on a worldwide adventure in search of unique experiences both in and out of the water. Join this fearless duo through stunning natural beauty and challenging, adrenaline-pumping activities!Thursday at 8:45PM</desc></programme>
<programme start="20251211134000 +0000" stop="20251211143000 +0000" channel="Canal Macau Ch. 92.mo"><title>Pantanal</title></programme>
<programme start="20251211143000 +0000" stop="20251211150500 +0000" channel="Canal Macau Ch. 92.mo"><title>TDM News</title><desc>30-minute daily news program in English with essential information about Macau, Greater China, the Asia-Pacific region and the rest of the world. It includes also sports and cultural news.Every day at 10:30PM</desc></programme>
<programme start="20251211150500 +0000" stop="20251211153000 +0000" channel="Canal Macau Ch. 92.mo"><title>Only In Bollywood</title><desc>Hollywood produces 500 films per year on average while Bollywood produces more than 1000. This series starts in Singapore where it establishes this cinematic genre reach in the region and the world, then follows several endearing characters and their stories of passion, grit, and a never-say-die attitude epitomizing the Bollywood dream in a way unparalleled to any other film industry.Thursday at 11:05PM.</desc></programme>
<programme start="20251211153000 +0000" stop="20251212053000 +0000" channel="Canal Macau Ch. 92.mo"><title>RTPi Live</title></programme>
<programme start="20251212053000 +0000" stop="20251212063000 +0000" channel="Canal Macau Ch. 92.mo"><title>News (RTPi) Delayed Broadcast</title></programme>
<programme start="20251212063000 +0000" stop="20251212070500 +0000" channel="Canal Macau Ch. 92.mo"><title>Chefs Friends S1</title></programme>
<programme start="20251212070500 +0000" stop="20251212075500 +0000" channel="Canal Macau Ch. 92.mo"><title>A Herdeira S2</title></programme>
<programme start="20251212075500 +0000" stop="20251212081000 +0000" channel="Canal Macau Ch. 92.mo"><title>Pocoyo S1</title></programme>
<programme start="20251212081000 +0000" stop="20251212085500 +0000" channel="Canal Macau Ch. 92.mo"><title>Red Moon</title></programme>
<programme start="20251212085500 +0000" stop="20251212094000 +0000" channel="Canal Macau Ch. 92.mo"><title>Kallys Mashup</title></programme>
<programme start="20251212094000 +0000" stop="20251212103000 +0000" channel="Canal Macau Ch. 92.mo"><title>Did You Know?</title><desc>If you had to explain science to someone who does not know a thing about it, how would you do?You no longer have to ask yourself this question since DID YOU KNOW? is here for that! Every episode is explaining clearly and simply your daily environment: health and well-being, human body, animals, earth, home, food, technology…Monday to Friday at 6:30PM</desc></programme>
<programme start="20251212103000 +0000" stop="20251212111000 +0000" channel="Canal Macau Ch. 92.mo"><title>TDM Entrevista - Carmen Amado Mendes (Repeated)</title></programme>
<programme start="20251212111000 +0000" stop="20251212120000 +0000" channel="Canal Macau Ch. 92.mo"><title>Cacau</title></programme>
<programme start="20251212120000 +0000" stop="20251212124500 +0000" channel="Canal Macau Ch. 92.mo"><title>Main News, Financial and Weather Report</title></programme>
<programme start="20251212124500 +0000" stop="20251212131500 +0000" channel="Canal Macau Ch. 92.mo"><title>Greater Bay Wealth</title><desc>Find out all about the economy and the latest businesses in the Greater Bay Area.Friday at 8:45PM</desc></programme>
<programme start="20251212131500 +0000" stop="20251212134000 +0000" channel="Canal Macau Ch. 92.mo"><title>Superstore S5</title><desc>The new season focuses on the aftermath of Mateos ICE detention, the staffs response to it, and the introduction of a new corporate directive called "Cloud 9.0," which includes a floor-cleaning robot that threatens their jobs…Friday at 9:15PM</desc></programme>
<programme start="20251212134000 +0000" stop="20251212143000 +0000" channel="Canal Macau Ch. 92.mo"><title>Pantanal</title></programme>
<programme start="20251212143000 +0000" stop="20251212150500 +0000" channel="Canal Macau Ch. 92.mo"><title>TDM News</title><desc>30-minute daily news program in English with essential information about Macau, Greater China, the Asia-Pacific region and the rest of the world. It includes also sports and cultural news.Every day at 10:30PM</desc></programme>
<programme start="20251212150500 +0000" stop="20251212160500 +0000" channel="Canal Macau Ch. 92.mo"><title>Equador</title></programme>
<programme start="20251212160500 +0000" stop="20251213053000 +0000" channel="Canal Macau Ch. 92.mo"><title>RTPi Live</title></programme>
<programme start="20251210160100 +0000" stop="20251210162500 +0000" channel="Ou Mun-Macau Ch.96.mo"><title>Passado Em Foco</title></programme>
<programme start="20251210162500 +0000" stop="20251210170000 +0000" channel="Ou Mun-Macau Ch.96.mo"><title>Emoções do Índico</title></programme>
<programme start="20251210170000 +0000" stop="20251210172000 +0000" channel="Ou Mun-Macau Ch.96.mo"><title>Macau Citywalk - World Heritage</title></programme>
<programme start="20251210172000 +0000" stop="20251210173000 +0000" channel="Ou Mun-Macau Ch.96.mo"><title>Livros Com Joao Guedes</title></programme>
<programme start="20251210173000 +0000" stop="20251210180000 +0000" channel="Ou Mun-Macau Ch.96.mo"><title>English News</title><desc>30-minute daily news program in English with essential information about Macau, Greater China, the Asia-Pacific region and the rest of the world. It includes also sports and cultural news.Every day at 10:30PM</desc></programme>
<programme start="20251210180000 +0000" stop="20251210184000 +0000" channel="Ou Mun-Macau Ch.96.mo"><title>Telejornal</title></programme>
<programme start="20251210184000 +0000" stop="20251210185000 +0000" channel="Ou Mun-Macau Ch.96.mo"><title>Patrimonio Cultural Intangível de Macau</title></programme>
<programme start="20251210185000 +0000" stop="20251210192000 +0000" channel="Ou Mun-Macau Ch.96.mo"><title>Repeat of Good Morning Macau</title></programme>
<programme start="20251210192000 +0000" stop="20251210195100 +0000" channel="Ou Mun-Macau Ch.96.mo"><title>Saboroso</title></programme>
<programme start="20251210195100 +0000" stop="20251210204000 +0000" channel="Ou Mun-Macau Ch.96.mo"><title>Hometown of Stars</title><desc>A Chinese television drama about three generations working to transform a desert into an oasis in western China, highlighting national efforts in development and the pursuit of ideals through actions related to the wine industry.Saturday at 7PM.</desc></programme>
<programme start="20251210204000 +0000" stop="20251210205000 +0000" channel="Ou Mun-Macau Ch.96.mo"><title>Home Cooking</title></programme>
<programme start="20251210205000 +0000" stop="20251210213000 +0000" channel="Ou Mun-Macau Ch.96.mo"><title>Telejornal</title></programme>
<programme start="20251210213000 +0000" stop="20251210215000 +0000" channel="Ou Mun-Macau Ch.96.mo"><title>Macau Citywalk - World Heritage</title></programme>
<programme start="20251210215000 +0000" stop="20251210220000 +0000" channel="Ou Mun-Macau Ch.96.mo"><title>Livros Com Joao Guedes</title></programme>
<programme start="20251210220000 +0000" stop="20251210222500 +0000" channel="Ou Mun-Macau Ch.96.mo"><title>Passado Em Foco</title></programme>
<programme start="20251210222500 +0000" stop="20251210230000 +0000" channel="Ou Mun-Macau Ch.96.mo"><title>Emoções do Índico</title></programme>
<programme start="20251210230000 +0000" stop="20251210232000 +0000" channel="Ou Mun-Macau Ch.96.mo"><title>Aqui Há Historia</title></programme>
<programme start="20251210232000 +0000" stop="20251210233000 +0000" channel="Ou Mun-Macau Ch.96.mo"><title>Patrimonio Cultural Intangível de Macau</title></programme>
<programme start="20251210233000 +0000" stop="20251211000000 +0000" channel="Ou Mun-Macau Ch.96.mo"><title>English News</title><desc>30-minute daily news program in English with essential information about Macau, Greater China, the Asia-Pacific region and the rest of the world. It includes also sports and cultural news.Every day at 10:30PM</desc></programme>
<programme start="20251211000000 +0000" stop="20251211003000 +0000" channel="Ou Mun-Macau Ch.96.mo"><title>Saboroso</title></programme>
<programme start="20251211003000 +0000" stop="20251211005000 +0000" channel="Ou Mun-Macau Ch.96.mo"><title>Our People, Our Life</title></programme>
<programme start="20251211005000 +0000" stop="20251211012000 +0000" channel="Ou Mun-Macau Ch.96.mo"><title>All About the Greater Bay Area</title></programme>
<programme start="20251211012000 +0000" stop="20251211020000 +0000" channel="Ou Mun-Macau Ch.96.mo"><title>Macau Sports 2025</title></programme>
<programme start="20251211020000 +0000" stop="20251211023100 +0000" channel="Ou Mun-Macau Ch.96.mo"><title>Cantonese News</title></programme>
<programme start="20251211023100 +0000" stop="20251211032000 +0000" channel="Ou Mun-Macau Ch.96.mo"><title>Hometown of Stars</title><desc>A Chinese television drama about three generations working to transform a desert into an oasis in western China, highlighting national efforts in development and the pursuit of ideals through actions related to the wine industry.Saturday at 7PM.</desc></programme>
<programme start="20251211032000 +0000" stop="20251211033000 +0000" channel="Ou Mun-Macau Ch.96.mo"><title>Home Cooking</title></programme>
<programme start="20251211033000 +0000" stop="20251211035000 +0000" channel="Ou Mun-Macau Ch.96.mo"><title>Macau Citywalk - World Heritage</title></programme>
<programme start="20251211035000 +0000" stop="20251211040000 +0000" channel="Ou Mun-Macau Ch.96.mo"><title>Livros Com Joao Guedes</title></programme>
<programme start="20251211040000 +0000" stop="20251211042500 +0000" channel="Ou Mun-Macau Ch.96.mo"><title>Passado Em Foco</title></programme>
<programme start="20251211042500 +0000" stop="20251211050000 +0000" channel="Ou Mun-Macau Ch.96.mo"><title>Emoções do Índico</title></programme>
<programme start="20251211050000 +0000" stop="20251211052000 +0000" channel="Ou Mun-Macau Ch.96.mo"><title>Aqui Há Historia</title></programme>
<programme start="20251211052000 +0000" stop="20251211060000 +0000" channel="Ou Mun-Macau Ch.96.mo"><title>Macau Sports 2025</title></programme>
<programme start="20251211060000 +0000" stop="20251211063000 +0000" channel="Ou Mun-Macau Ch.96.mo"><title>Cantonese News</title></programme>
<programme start="20251211063000 +0000" stop="20251211065000 +0000" channel="Ou Mun-Macau Ch.96.mo"><title>Our People, Our Life</title></programme>
<programme start="20251211065000 +0000" stop="20251211070000 +0000" channel="Ou Mun-Macau Ch.96.mo"><title>Home Cooking</title></programme>
<programme start="20251211070000 +0000" stop="20251211074100 +0000" channel="Ou Mun-Macau Ch.96.mo"><title>Telejornal</title></programme>
<programme start="20251211074100 +0000" stop="20251211083000 +0000" channel="Ou Mun-Macau Ch.96.mo"><title>Hometown of Stars</title><desc>A Chinese television drama about three generations working to transform a desert into an oasis in western China, highlighting national efforts in development and the pursuit of ideals through actions related to the wine industry.Saturday at 7PM.</desc></programme>
<programme start="20251211083000 +0000" stop="20251211085500 +0000" channel="Ou Mun-Macau Ch.96.mo"><title>Passado Em Foco</title></programme>
<programme start="20251211085500 +0000" stop="20251211093000 +0000" channel="Ou Mun-Macau Ch.96.mo"><title>Emoções do Índico</title></programme>
<programme start="20251211093000 +0000" stop="20251211095000 +0000" channel="Ou Mun-Macau Ch.96.mo"><title>Aqui Há Historia</title></programme>
<programme start="20251211095000 +0000" stop="20251211100000 +0000" channel="Ou Mun-Macau Ch.96.mo"><title>Patrimonio Cultural Intangível de Macau</title></programme>
<programme start="20251211100000 +0000" stop="20251211103000 +0000" channel="Ou Mun-Macau Ch.96.mo"><title>English News</title><desc>30-minute daily news program in English with essential information about Macau, Greater China, the Asia-Pacific region and the rest of the world. It includes also sports and cultural news.Every day at 10:30PM</desc></programme>
<programme start="20251211103000 +0000" stop="20251211110000 +0000" channel="Ou Mun-Macau Ch.96.mo"><title>Saboroso</title></programme>
<programme start="20251211110000 +0000" stop="20251211120000 +0000" channel="Ou Mun-Macau Ch.96.mo"><title>Cantonese News</title></programme>
<programme start="20251211120000 +0000" stop="20251211122000 +0000" channel="Ou Mun-Macau Ch.96.mo"><title>Our People, Our Life</title></programme>
<programme start="20251211122000 +0000" stop="20251211130000 +0000" channel="Ou Mun-Macau Ch.96.mo"><title>Macau Sports 2025</title></programme>
<programme start="20251211130000 +0000" stop="20251211133000 +0000" channel="Ou Mun-Macau Ch.96.mo"><title>All About the Greater Bay Area</title></programme>
<programme start="20251211133000 +0000" stop="20251211135000 +0000" channel="Ou Mun-Macau Ch.96.mo"><title>Macau Citywalk - World Heritage</title></programme>
<programme start="20251211135000 +0000" stop="20251211140000 +0000" channel="Ou Mun-Macau Ch.96.mo"><title>Livros Com Joao Guedes</title></programme>
<programme start="20251211140000 +0000" stop="20251211145000 +0000" channel="Ou Mun-Macau Ch.96.mo"><title>Cantonese News</title></programme>
<programme start="20251211145000 +0000" stop="20251211150000 +0000" channel="Ou Mun-Macau Ch.96.mo"><title>Home Cooking</title></programme>
<programme start="20251211150000 +0000" stop="20251211154000 +0000" channel="Ou Mun-Macau Ch.96.mo"><title>Telejornal</title></programme>
<programme start="20251211154000 +0000" stop="20251211160100 +0000" channel="Ou Mun-Macau Ch.96.mo"><title>Our People, Our Life</title></programme>
<programme start="20251211160100 +0000" stop="20251211162000 +0000" channel="Ou Mun-Macau Ch.96.mo"><title>Passado Em Foco</title></programme>
<programme start="20251211162000 +0000" stop="20251211163000 +0000" channel="Ou Mun-Macau Ch.96.mo"><title>Livros Com Joao Guedes</title></programme>
<programme start="20251211163000 +0000" stop="20251211170000 +0000" channel="Ou Mun-Macau Ch.96.mo"><title>Emoções do Índico</title></programme>
<programme start="20251211170000 +0000" stop="20251211173000 +0000" channel="Ou Mun-Macau Ch.96.mo"><title>Macau Citywalk - World Heritage</title></programme>
<programme start="20251211173000 +0000" stop="20251211180000 +0000" channel="Ou Mun-Macau Ch.96.mo"><title>English News</title><desc>30-minute daily news program in English with essential information about Macau, Greater China, the Asia-Pacific region and the rest of the world. It includes also sports and cultural news.Every day at 10:30PM</desc></programme>
<programme start="20251211180000 +0000" stop="20251211184000 +0000" channel="Ou Mun-Macau Ch.96.mo"><title>Telejornal</title></programme>
<programme start="20251211184000 +0000" stop="20251211185000 +0000" channel="Ou Mun-Macau Ch.96.mo"><title>Patrimonio Cultural Intangível de Macau</title></programme>
<programme start="20251211185000 +0000" stop="20251211192000 +0000" channel="Ou Mun-Macau Ch.96.mo"><title>Repeat of Good Morning Macau</title></programme>
<programme start="20251211192000 +0000" stop="20251211195100 +0000" channel="Ou Mun-Macau Ch.96.mo"><title>Saboroso</title></programme>
<programme start="20251211195100 +0000" stop="20251211204000 +0000" channel="Ou Mun-Macau Ch.96.mo"><title>Hometown of Stars</title><desc>A Chinese television drama about three generations working to transform a desert into an oasis in western China, highlighting national efforts in development and the pursuit of ideals through actions related to the wine industry.Saturday at 7PM.</desc></programme>
<programme start="20251211204000 +0000" stop="20251211205000 +0000" channel="Ou Mun-Macau Ch.96.mo"><title>Home Cooking</title></programme>
<programme start="20251211205000 +0000" stop="20251211213000 +0000" channel="Ou Mun-Macau Ch.96.mo"><title>Telejornal</title></programme>
<programme start="20251211213000 +0000" stop="20251211220000 +0000" channel="Ou Mun-Macau Ch.96.mo"><title>Macau Citywalk - World Heritage</title></programme>
<programme start="20251211220000 +0000" stop="20251211222000 +0000" channel="Ou Mun-Macau Ch.96.mo"><title>Passado Em Foco</title></programme>
<programme start="20251211222000 +0000" stop="20251211223000 +0000" channel="Ou Mun-Macau Ch.96.mo"><title>Livros Com Joao Guedes</title></programme>
<programme start="20251211223000 +0000" stop="20251211230000 +0000" channel="Ou Mun-Macau Ch.96.mo"><title>Emoções do Índico</title></programme>
<programme start="20251211230000 +0000" stop="20251211233000 +0000" channel="Ou Mun-Macau Ch.96.mo"><title>#Hipsters Choice</title></programme>
<programme start="20251211233000 +0000" stop="20251212000000 +0000" channel="Ou Mun-Macau Ch.96.mo"><title>English News</title><desc>30-minute daily news program in English with essential information about Macau, Greater China, the Asia-Pacific region and the rest of the world. It includes also sports and cultural news.Every day at 10:30PM</desc></programme>
<programme start="20251212000000 +0000" stop="20251212003000 +0000" channel="Ou Mun-Macau Ch.96.mo"><title>Saboroso</title></programme>
<programme start="20251212003000 +0000" stop="20251212005000 +0000" channel="Ou Mun-Macau Ch.96.mo"><title>Our People, Our Life</title></programme>
<programme start="20251212005000 +0000" stop="20251212012000 +0000" channel="Ou Mun-Macau Ch.96.mo"><title>All About the Greater Bay Area</title></programme>
<programme start="20251212012000 +0000" stop="20251212020000 +0000" channel="Ou Mun-Macau Ch.96.mo"><title>Wind and Fire</title></programme>
<programme start="20251212020000 +0000" stop="20251212023100 +0000" channel="Ou Mun-Macau Ch.96.mo"><title>Cantonese News</title></programme>
<programme start="20251212023100 +0000" stop="20251212032000 +0000" channel="Ou Mun-Macau Ch.96.mo"><title>Hometown of Stars</title><desc>A Chinese television drama about three generations working to transform a desert into an oasis in western China, highlighting national efforts in development and the pursuit of ideals through actions related to the wine industry.Saturday at 7PM.</desc></programme>
<programme start="20251212032000 +0000" stop="20251212033000 +0000" channel="Ou Mun-Macau Ch.96.mo"><title>Patrimonio Cultural Intangível de Macau</title></programme>
<programme start="20251212033000 +0000" stop="20251212040000 +0000" channel="Ou Mun-Macau Ch.96.mo"><title>Macau Citywalk - World Heritage</title></programme>
<programme start="20251212040000 +0000" stop="20251212042000 +0000" channel="Ou Mun-Macau Ch.96.mo"><title>Passado Em Foco</title></programme>
<programme start="20251212042000 +0000" stop="20251212045000 +0000" channel="Ou Mun-Macau Ch.96.mo"><title>Emoções do Índico</title></programme>
<programme start="20251212045000 +0000" stop="20251212052000 +0000" channel="Ou Mun-Macau Ch.96.mo"><title>#Hipsters Choice</title></programme>
<programme start="20251212052000 +0000" stop="20251212060000 +0000" channel="Ou Mun-Macau Ch.96.mo"><title>Wind and Fire</title></programme>
<programme start="20251212060000 +0000" stop="20251212063000 +0000" channel="Ou Mun-Macau Ch.96.mo"><title>Cantonese News</title></programme>
<programme start="20251212063000 +0000" stop="20251212065000 +0000" channel="Ou Mun-Macau Ch.96.mo"><title>Our People, Our Life</title></programme>
<programme start="20251212065000 +0000" stop="20251212070000 +0000" channel="Ou Mun-Macau Ch.96.mo"><title>Home Cooking</title></programme>
<programme start="20251212070000 +0000" stop="20251212074100 +0000" channel="Ou Mun-Macau Ch.96.mo"><title>Telejornal</title></programme>
<programme start="20251212074100 +0000" stop="20251212083000 +0000" channel="Ou Mun-Macau Ch.96.mo"><title>Hometown of Stars</title><desc>A Chinese television drama about three generations working to transform a desert into an oasis in western China, highlighting national efforts in development and the pursuit of ideals through actions related to the wine industry.Saturday at 7PM.</desc></programme>
<programme start="20251212083000 +0000" stop="20251212085000 +0000" channel="Ou Mun-Macau Ch.96.mo"><title>Passado Em Foco</title></programme>
<programme start="20251212085000 +0000" stop="20251212090000 +0000" channel="Ou Mun-Macau Ch.96.mo"><title>Patrimonio Cultural Intangível de Macau</title></programme>
<programme start="20251212090000 +0000" stop="20251212093000 +0000" channel="Ou Mun-Macau Ch.96.mo"><title>Emoções do Índico</title></programme>
<programme start="20251212093000 +0000" stop="20251212100000 +0000" channel="Ou Mun-Macau Ch.96.mo"><title>#Hipsters Choice</title></programme>
<programme start="20251212100000 +0000" stop="20251212103000 +0000" channel="Ou Mun-Macau Ch.96.mo"><title>English News</title><desc>30-minute daily news program in English with essential information about Macau, Greater China, the Asia-Pacific region and the rest of the world. It includes also sports and cultural news.Every day at 10:30PM</desc></programme>
<programme start="20251212103000 +0000" stop="20251212110000 +0000" channel="Ou Mun-Macau Ch.96.mo"><title>Saboroso</title></programme>
<programme start="20251212110000 +0000" stop="20251212120000 +0000" channel="Ou Mun-Macau Ch.96.mo"><title>Cantonese News</title></programme>
<programme start="20251212120000 +0000" stop="20251212122000 +0000" channel="Ou Mun-Macau Ch.96.mo"><title>Our People, Our Life</title></programme>
<programme start="20251212122000 +0000" stop="20251212130000 +0000" channel="Ou Mun-Macau Ch.96.mo"><title>Wind and Fire</title></programme>
<programme start="20251212130000 +0000" stop="20251212133000 +0000" channel="Ou Mun-Macau Ch.96.mo"><title>All About the Greater Bay Area</title></programme>
<programme start="20251212133000 +0000" stop="20251212140000 +0000" channel="Ou Mun-Macau Ch.96.mo"><title>Macau Citywalk - World Heritage</title></programme>
<programme start="20251212140000 +0000" stop="20251212145000 +0000" channel="Ou Mun-Macau Ch.96.mo"><title>Cantonese News</title></programme>
<programme start="20251212145000 +0000" stop="20251212150000 +0000" channel="Ou Mun-Macau Ch.96.mo"><title>Home Cooking</title></programme>
<programme start="20251212150000 +0000" stop="20251212154000 +0000" channel="Ou Mun-Macau Ch.96.mo"><title>Telejornal</title></programme>
<programme start="20251212154000 +0000" stop="20251212160100 +0000" channel="Ou Mun-Macau Ch.96.mo"><title>Our People, Our Life</title></programme>
<programme start="20251212160100 +0000" stop="20251212163000 +0000" channel="Ou Mun-Macau Ch.96.mo"><title>Greater Bay Wealth</title><desc>Find out all about the economy and the latest businesses in the Greater Bay Area.Friday at 8:45PM</desc></programme>
<programme start="20251212163000 +0000" stop="20251212170000 +0000" channel="Ou Mun-Macau Ch.96.mo"><title>Emoções do Índico</title></programme>
<programme start="20251212170000 +0000" stop="20251212172000 +0000" channel="Ou Mun-Macau Ch.96.mo"><title>Macau Citywalk - World Heritage</title></programme>
<programme start="20251212172000 +0000" stop="20251212173000 +0000" channel="Ou Mun-Macau Ch.96.mo"><title>Livros Com Joao Guedes</title></programme>
<programme start="20251212173000 +0000" stop="20251212180000 +0000" channel="Ou Mun-Macau Ch.96.mo"><title>English News</title><desc>30-minute daily news program in English with essential information about Macau, Greater China, the Asia-Pacific region and the rest of the world. It includes also sports and cultural news.Every day at 10:30PM</desc></programme>
<programme start="20251212180000 +0000" stop="20251212184000 +0000" channel="Ou Mun-Macau Ch.96.mo"><title>Telejornal</title></programme>
<programme start="20251212184000 +0000" stop="20251212185000 +0000" channel="Ou Mun-Macau Ch.96.mo"><title>Patrimonio Cultural Intangível de Macau</title></programme>
<programme start="20251212185000 +0000" stop="20251212192000 +0000" channel="Ou Mun-Macau Ch.96.mo"><title>Repeat of Good Morning Macau</title></programme>
<programme start="20251212192000 +0000" stop="20251212195100 +0000" channel="Ou Mun-Macau Ch.96.mo"><title>The Encyclopedia Of Classic Cars</title></programme>
<programme start="20251212195100 +0000" stop="20251212204000 +0000" channel="Ou Mun-Macau Ch.96.mo"><title>Hometown of Stars</title><desc>A Chinese television drama about three generations working to transform a desert into an oasis in western China, highlighting national efforts in development and the pursuit of ideals through actions related to the wine industry.Saturday at 7PM.</desc></programme>
<programme start="20251212204000 +0000" stop="20251212205000 +0000" channel="Ou Mun-Macau Ch.96.mo"><title>Home Cooking</title></programme>
<programme start="20251212205000 +0000" stop="20251212213000 +0000" channel="Ou Mun-Macau Ch.96.mo"><title>Telejornal</title></programme>
<programme start="20251212213000 +0000" stop="20251212215000 +0000" channel="Ou Mun-Macau Ch.96.mo"><title>Macau Citywalk - World Heritage</title></programme>
<programme start="20251212215000 +0000" stop="20251212220000 +0000" channel="Ou Mun-Macau Ch.96.mo"><title>Livros Com Joao Guedes</title></programme>
<programme start="20251212220000 +0000" stop="20251212223000 +0000" channel="Ou Mun-Macau Ch.96.mo"><title>Greater Bay Wealth</title><desc>Find out all about the economy and the latest businesses in the Greater Bay Area.Friday at 8:45PM</desc></programme>
<programme start="20251212223000 +0000" stop="20251212230000 +0000" channel="Ou Mun-Macau Ch.96.mo"><title>Emoções do Índico</title></programme>
<programme start="20251212230000 +0000" stop="20251212233000 +0000" channel="Ou Mun-Macau Ch.96.mo"><title>#Hipsters Choice</title></programme>
<programme start="20251212233000 +0000" stop="20251213000000 +0000" channel="Ou Mun-Macau Ch.96.mo"><title>English News</title><desc>30-minute daily news program in English with essential information about Macau, Greater China, the Asia-Pacific region and the rest of the world. It includes also sports and cultural news.Every day at 10:30PM</desc></programme>
<programme start="20251213000000 +0000" stop="20251213003000 +0000" channel="Ou Mun-Macau Ch.96.mo"><title>The Encyclopedia Of Classic Cars</title></programme>
<programme start="20251213003000 +0000" stop="20251213005000 +0000" channel="Ou Mun-Macau Ch.96.mo"><title>Our People, Our Life</title></programme>
<programme start="20251213005000 +0000" stop="20251213012000 +0000" channel="Ou Mun-Macau Ch.96.mo"><title>All About the Greater Bay Area</title></programme>
<programme start="20251213012000 +0000" stop="20251213015000 +0000" channel="Ou Mun-Macau Ch.96.mo"><title>Macau News File</title></programme>
<programme start="20251213015000 +0000" stop="20251213020000 +0000" channel="Ou Mun-Macau Ch.96.mo"><title>Patrimonio Cultural Intangível de Macau</title></programme>
<programme start="20251213020000 +0000" stop="20251213023100 +0000" channel="Ou Mun-Macau Ch.96.mo"><title>Cantonese News</title></programme>
<programme start="20251213023100 +0000" stop="20251213032000 +0000" channel="Ou Mun-Macau Ch.96.mo"><title>Hometown of Stars</title><desc>A Chinese television drama about three generations working to transform a desert into an oasis in western China, highlighting national efforts in development and the pursuit of ideals through actions related to the wine industry.Saturday at 7PM.</desc></programme>
<programme start="20251213032000 +0000" stop="20251213033000 +0000" channel="Ou Mun-Macau Ch.96.mo"><title>Home Cooking</title></programme>
<programme start="20251210230000 +0000" stop="20251210231500 +0000" channel="Rádio Macau FM98.mo"><title>Noticiário</title></programme>
<programme start="20251210231500 +0000" stop="20251210232000 +0000" channel="Rádio Macau FM98.mo"><title>Cafe da Manha</title></programme>
<programme start="20251210232000 +0000" stop="20251210233000 +0000" channel="Rádio Macau FM98.mo"><title>Revista de Imprensa</title></programme>
<programme start="20251210233000 +0000" stop="20251210234500 +0000" channel="Rádio Macau FM98.mo"><title>Síntese Informativa</title></programme>
<programme start="20251210234500 +0000" stop="20251211000000 +0000" channel="Rádio Macau FM98.mo"><title>Top Musica</title></programme>
<programme start="20251211000000 +0000" stop="20251211001500 +0000" channel="Rádio Macau FM98.mo"><title>Noticiário</title></programme>
<programme start="20251211001500 +0000" stop="20251211002000 +0000" channel="Rádio Macau FM98.mo"><title>Cafe da Manha</title></programme>
<programme start="20251211002000 +0000" stop="20251211003000 +0000" channel="Rádio Macau FM98.mo"><title>Revista de Imprensa</title></programme>
<programme start="20251211003000 +0000" stop="20251211010000 +0000" channel="Rádio Macau FM98.mo"><title>Síntese Informativa</title></programme>
<programme start="20251211010000 +0000" stop="20251211011500 +0000" channel="Rádio Macau FM98.mo"><title>Noticiário</title></programme>
<programme start="20251211011500 +0000" stop="20251211020000 +0000" channel="Rádio Macau FM98.mo"><title>Cafe da Manha</title></programme>
<programme start="20251211020000 +0000" stop="20251211021500 +0000" channel="Rádio Macau FM98.mo"><title>Noticiário</title></programme>
<programme start="20251211021500 +0000" stop="20251211033000 +0000" channel="Rádio Macau FM98.mo"><title>Emissao em Directo</title></programme>
<programme start="20251211033000 +0000" stop="20251211040000 +0000" channel="Rádio Macau FM98.mo"><title>Revista de Imprensa</title></programme>
<programme start="20251211040000 +0000" stop="20251211041500 +0000" channel="Rádio Macau FM98.mo"><title>Jornal de Desporto</title></programme>
<programme start="20251211041500 +0000" stop="20251211043000 +0000" channel="Rádio Macau FM98.mo"><title>Emissao em Directo</title></programme>
<programme start="20251211043000 +0000" stop="20251211050000 +0000" channel="Rádio Macau FM98.mo"><title>Economia e Negocios</title></programme>
<programme start="20251211050000 +0000" stop="20251211051500 +0000" channel="Rádio Macau FM98.mo"><title>Noticiário</title></programme>
<programme start="20251211051500 +0000" stop="20251211060000 +0000" channel="Rádio Macau FM98.mo"><title>Emissao em Directo</title></programme>
<programme start="20251211060000 +0000" stop="20251211061500 +0000" channel="Rádio Macau FM98.mo"><title>Noticiário</title></programme>
<programme start="20251211061500 +0000" stop="20251211063000 +0000" channel="Rádio Macau FM98.mo"><title>Emissao em Directo</title></programme>
<programme start="20251211063000 +0000" stop="20251211070000 +0000" channel="Rádio Macau FM98.mo"><title>Som da Semana</title></programme>
<programme start="20251211070000 +0000" stop="20251211071500 +0000" channel="Rádio Macau FM98.mo"><title>Noticiário</title></programme>
<programme start="20251211071500 +0000" stop="20251211080000 +0000" channel="Rádio Macau FM98.mo"><title>Emissao em Directo</title></programme>
<programme start="20251211080000 +0000" stop="20251211100000 +0000" channel="Rádio Macau FM98.mo"><title>Emissao em Directo</title></programme>
<programme start="20251211100000 +0000" stop="20251211103000 +0000" channel="Rádio Macau FM98.mo"><title>Noticiário</title></programme>
<programme start="20251211103000 +0000" stop="20251211110000 +0000" channel="Rádio Macau FM98.mo"><title>Som da Semana</title></programme>
<programme start="20251211110000 +0000" stop="20251211120000 +0000" channel="Rádio Macau FM98.mo"><title>Noticiário</title></programme>
<programme start="20251211120000 +0000" stop="20251211230000 +0000" channel="Rádio Macau FM98.mo"><title>Ligaçao à Antena 1</title></programme>
<programme start="20251211230000 +0000" stop="20251211231500 +0000" channel="Rádio Macau FM98.mo"><title>Noticiário</title></programme>
<programme start="20251211231500 +0000" stop="20251211232000 +0000" channel="Rádio Macau FM98.mo"><title>Cafe da Manha</title></programme>
<programme start="20251211232000 +0000" stop="20251211233000 +0000" channel="Rádio Macau FM98.mo"><title>Revista de Imprensa</title></programme>
<programme start="20251211233000 +0000" stop="20251211234500 +0000" channel="Rádio Macau FM98.mo"><title>Síntese Informativa</title></programme>
<programme start="20251211234500 +0000" stop="20251212000000 +0000" channel="Rádio Macau FM98.mo"><title>Top Musica</title></programme>
<programme start="20251212000000 +0000" stop="20251212001500 +0000" channel="Rádio Macau FM98.mo"><title>Noticiário</title></programme>
<programme start="20251212001500 +0000" stop="20251212002000 +0000" channel="Rádio Macau FM98.mo"><title>Cafe da Manha</title></programme>
<programme start="20251212002000 +0000" stop="20251212003000 +0000" channel="Rádio Macau FM98.mo"><title>Revista de Imprensa</title></programme>
<programme start="20251212003000 +0000" stop="20251212004500 +0000" channel="Rádio Macau FM98.mo"><title>Síntese Informativa</title></programme>
<programme start="20251212004500 +0000" stop="20251212010000 +0000" channel="Rádio Macau FM98.mo"><title>Plano B</title></programme>
<programme start="20251212010000 +0000" stop="20251212011500 +0000" channel="Rádio Macau FM98.mo"><title>Noticiário</title></programme>
<programme start="20251212011500 +0000" stop="20251212020000 +0000" channel="Rádio Macau FM98.mo"><title>Cafe da Manha</title></programme>
<programme start="20251212020000 +0000" stop="20251212021500 +0000" channel="Rádio Macau FM98.mo"><title>Noticiário</title></programme>
<programme start="20251212021500 +0000" stop="20251212033000 +0000" channel="Rádio Macau FM98.mo"><title>Emissao em Directo</title></programme>
<programme start="20251212033000 +0000" stop="20251212040000 +0000" channel="Rádio Macau FM98.mo"><title>Revista de Imprensa</title></programme>
<programme start="20251212040000 +0000" stop="20251212041500 +0000" channel="Rádio Macau FM98.mo"><title>Jornal de Desporto</title></programme>
<programme start="20251212041500 +0000" stop="20251212043000 +0000" channel="Rádio Macau FM98.mo"><title>Emissao em Directo</title></programme>
<programme start="20251212043000 +0000" stop="20251212050000 +0000" channel="Rádio Macau FM98.mo"><title>Economia e Negocios</title></programme>
<programme start="20251212050000 +0000" stop="20251212051500 +0000" channel="Rádio Macau FM98.mo"><title>Noticiário</title></programme>
<programme start="20251212051500 +0000" stop="20251212060000 +0000" channel="Rádio Macau FM98.mo"><title>Emissao em Directo</title></programme>
<programme start="20251212060000 +0000" stop="20251212061500 +0000" channel="Rádio Macau FM98.mo"><title>Noticiário</title></programme>
<programme start="20251212061500 +0000" stop="20251212063000 +0000" channel="Rádio Macau FM98.mo"><title>Emissao em Directo</title></programme>
<programme start="20251212063000 +0000" stop="20251212070000 +0000" channel="Rádio Macau FM98.mo"><title>Som da Semana</title></programme>
<programme start="20251212070000 +0000" stop="20251212071500 +0000" channel="Rádio Macau FM98.mo"><title>Noticiário</title></programme>
<programme start="20251212071500 +0000" stop="20251212080000 +0000" channel="Rádio Macau FM98.mo"><title>Emissao em Directo</title></programme>
<programme start="20251212080000 +0000" stop="20251212100000 +0000" channel="Rádio Macau FM98.mo"><title>Fado a Oriente</title></programme>
<programme start="20251212100000 +0000" stop="20251212101500 +0000" channel="Rádio Macau FM98.mo"><title>Noticiário</title></programme>
<programme start="20251212101500 +0000" stop="20251212103000 +0000" channel="Rádio Macau FM98.mo"><title>Plano B</title></programme>
<programme start="20251212103000 +0000" stop="20251212110000 +0000" channel="Rádio Macau FM98.mo"><title>Som da Semana</title></programme>
<programme start="20251212110000 +0000" stop="20251212111500 +0000" channel="Rádio Macau FM98.mo"><title>Noticiário</title></programme>
<programme start="20251212111500 +0000" stop="20251212120000 +0000" channel="Rádio Macau FM98.mo"><title>Frequencia Academica</title></programme>
<programme start="20251212120000 +0000" stop="20251213000000 +0000" channel="Rádio Macau FM98.mo"><title>Ligaçao à Antena 1</title></programme>
<programme start="20251213000000 +0000" stop="20251213001500 +0000" channel="Rádio Macau FM98.mo"><title>Noticiário</title></programme>
<programme start="20251213001500 +0000" stop="20251213010000 +0000" channel="Rádio Macau FM98.mo"><title>Emissao em Directo</title></programme>
<programme start="20251213010000 +0000" stop="20251213011500 +0000" channel="Rádio Macau FM98.mo"><title>Noticiário</title></programme>
<programme start="20251213011500 +0000" stop="20251213020000 +0000" channel="Rádio Macau FM98.mo"><title>Emissao em Directo</title></programme>
<programme start="20251213020000 +0000" stop="20251213021500 +0000" channel="Rádio Macau FM98.mo"><title>Noticiário</title></programme>
<programme start="20251213021500 +0000" stop="20251213023000 +0000" channel="Rádio Macau FM98.mo"><title>Emissao em Directo</title></programme>
<programme start="20251213023000 +0000" stop="20251213050000 +0000" channel="Rádio Macau FM98.mo"><title>Bloco de Notas</title></programme>
<programme start="20251211015900 +0000" stop="20251211020000 +0000" channel="TDM Entertainment Ch.95.mo"><title>Open</title></programme>
<programme start="20251211020000 +0000" stop="20251211023000 +0000" channel="TDM Entertainment Ch.95.mo"><title>News Summary</title></programme>
<programme start="20251211023000 +0000" stop="20251211031000 +0000" channel="TDM Entertainment Ch.95.mo"><title>Treasures of Ancient Shu</title></programme>
<programme start="20251211031000 +0000" stop="20251211033000 +0000" channel="TDM Entertainment Ch.95.mo"><title>Our People, Our Life</title></programme>
<programme start="20251211033000 +0000" stop="20251211040000 +0000" channel="TDM Entertainment Ch.95.mo"><title>All About the Greater Bay Area</title></programme>
<programme start="20251211040000 +0000" stop="20251211045000 +0000" channel="TDM Entertainment Ch.95.mo"><title>The Fearless</title></programme>
<programme start="20251211045000 +0000" stop="20251211050000 +0000" channel="TDM Entertainment Ch.95.mo"><title>My Land, My People</title></programme>
<programme start="20251211050000 +0000" stop="20251211050500 +0000" channel="TDM Entertainment Ch.95.mo"><title>Noon Weather Report</title></programme>
<programme start="20251211050500 +0000" stop="20251211051500 +0000" channel="TDM Entertainment Ch.95.mo"><title>Hengqin Guide</title></programme>
<programme start="20251211051500 +0000" stop="20251211052000 +0000" channel="TDM Entertainment Ch.95.mo"><title>Good Morning Macau : Highlights</title></programme>
<programme start="20251211052000 +0000" stop="20251211052500 +0000" channel="TDM Entertainment Ch.95.mo"><title>"You Ask, We Answer" Guangdong-Macao Laws Livestream</title></programme>
<programme start="20251211052500 +0000" stop="20251211053000 +0000" channel="TDM Entertainment Ch.95.mo"><title>TDM Focus</title></programme>
<programme start="20251211053000 +0000" stop="20251211060000 +0000" channel="TDM Entertainment Ch.95.mo"><title>Noon News</title></programme>
<programme start="20251211060000 +0000" stop="20251211070000 +0000" channel="TDM Entertainment Ch.95.mo"><title>Financial Daily</title></programme>
<programme start="20251211070000 +0000" stop="20251211074000 +0000" channel="TDM Entertainment Ch.95.mo"><title>City News Net of China (Repeat)</title></programme>
<programme start="20251211074000 +0000" stop="20251211080000 +0000" channel="TDM Entertainment Ch.95.mo"><title>Our People, Our Life</title></programme>
<programme start="20251211080000 +0000" stop="20251211084500 +0000" channel="TDM Entertainment Ch.95.mo"><title>The Legend of Silk Manuscripts</title></programme>
<programme start="20251211084500 +0000" stop="20251211092000 +0000" channel="TDM Entertainment Ch.95.mo"><title>Health Consultations</title></programme>
<programme start="20251211092000 +0000" stop="20251211093000 +0000" channel="TDM Entertainment Ch.95.mo"><title>Meet Generation Z</title></programme>
<programme start="20251211093000 +0000" stop="20251211095900 +0000" channel="TDM Entertainment Ch.95.mo"><title>Repeat of Good Morning Macau</title></programme>
<programme start="20251211095900 +0000" stop="20251211100000 +0000" channel="TDM Entertainment Ch.95.mo"><title>TDM Focus</title></programme>
<programme start="20251211100000 +0000" stop="20251211102500 +0000" channel="TDM Entertainment Ch.95.mo"><title>Dream For Rim S2</title></programme>
<programme start="20251211102500 +0000" stop="20251211120000 +0000" channel="TDM Entertainment Ch.95.mo"><title>The Listener</title></programme>
<programme start="20251211120000 +0000" stop="20251211125000 +0000" channel="TDM Entertainment Ch.95.mo"><title>Ways To School</title></programme>
<programme start="20251211125000 +0000" stop="20251211130000 +0000" channel="TDM Entertainment Ch.95.mo"><title>Shanghai Craftsmanship</title></programme>
<programme start="20251211130000 +0000" stop="20251211143500 +0000" channel="TDM Entertainment Ch.95.mo"><title>The Listener</title></programme>
<programme start="20251211143500 +0000" stop="20251211150500 +0000" channel="TDM Entertainment Ch.95.mo"><title>Xinjiang Now and Then</title></programme>
<programme start="20251211150500 +0000" stop="20251211151500 +0000" channel="TDM Entertainment Ch.95.mo"><title>World Heritage Sites</title></programme>
<programme start="20251211151500 +0000" stop="20251211160100 +0000" channel="TDM Entertainment Ch.95.mo"><title>My Star Bride</title></programme>
<programme start="20251211160100 +0000" stop="20251211174000 +0000" channel="TDM Entertainment Ch.95.mo"><title>USA : The Most Dangerous Country In The World</title></programme>
<programme start="20251211174000 +0000" stop="20251211194500 +0000" channel="TDM Entertainment Ch.95.mo"><title>UEFA Europa Conference League 2025/2026 : Fiorentina vs Dynamo Kyiv (Live)</title></programme>
<programme start="20251211194500 +0000" stop="20251211195500 +0000" channel="TDM Entertainment Ch.95.mo"><title>Slowstep Yore</title></programme>
<programme start="20251211195500 +0000" stop="20251211220000 +0000" channel="TDM Entertainment Ch.95.mo"><title>UEFA Europa League 2025/2026 : Basel vs Aston Villa (Live)</title></programme>
<programme start="20251211220000 +0000" stop="20251212015900 +0000" channel="TDM Entertainment Ch.95.mo"><title>Close</title></programme>
<programme start="20251212015900 +0000" stop="20251212020000 +0000" channel="TDM Entertainment Ch.95.mo"><title>Open</title></programme>
<programme start="20251212020000 +0000" stop="20251212023000 +0000" channel="TDM Entertainment Ch.95.mo"><title>News Summary</title></programme>
<programme start="20251212023000 +0000" stop="20251212031000 +0000" channel="TDM Entertainment Ch.95.mo"><title>Wind and Fire (Repeat)</title></programme>
<programme start="20251212031000 +0000" stop="20251212033000 +0000" channel="TDM Entertainment Ch.95.mo"><title>Our People, Our Life</title></programme>
<programme start="20251212033000 +0000" stop="20251212040000 +0000" channel="TDM Entertainment Ch.95.mo"><title>All About the Greater Bay Area</title></programme>
<programme start="20251212040000 +0000" stop="20251212045000 +0000" channel="TDM Entertainment Ch.95.mo"><title>The Fearless</title></programme>
<programme start="20251212045000 +0000" stop="20251212050000 +0000" channel="TDM Entertainment Ch.95.mo"><title>My Land, My People</title></programme>
<programme start="20251212050000 +0000" stop="20251212050500 +0000" channel="TDM Entertainment Ch.95.mo"><title>Noon Weather Report</title></programme>
<programme start="20251212050500 +0000" stop="20251212051500 +0000" channel="TDM Entertainment Ch.95.mo"><title>Focus China</title></programme>
<programme start="20251212051500 +0000" stop="20251212052000 +0000" channel="TDM Entertainment Ch.95.mo"><title>Good Morning Macau : Highlights</title></programme>
<programme start="20251212052000 +0000" stop="20251212052500 +0000" channel="TDM Entertainment Ch.95.mo"><title>Having Fun in Tang Poetry</title></programme>
<programme start="20251212052500 +0000" stop="20251212053000 +0000" channel="TDM Entertainment Ch.95.mo"><title>TDM Focus</title></programme>
<programme start="20251212053000 +0000" stop="20251212060000 +0000" channel="TDM Entertainment Ch.95.mo"><title>Noon News</title></programme>
<programme start="20251212060000 +0000" stop="20251212070000 +0000" channel="TDM Entertainment Ch.95.mo"><title>Financial Daily</title></programme>
<programme start="20251212070000 +0000" stop="20251212074000 +0000" channel="TDM Entertainment Ch.95.mo"><title>Wind and Fire (Repeat)</title></programme>
<programme start="20251212074000 +0000" stop="20251212080000 +0000" channel="TDM Entertainment Ch.95.mo"><title>Our People, Our Life</title></programme>
<programme start="20251212080000 +0000" stop="20251212093000 +0000" channel="TDM Entertainment Ch.95.mo"><title>Music Bank</title></programme>
<programme start="20251212093000 +0000" stop="20251212095900 +0000" channel="TDM Entertainment Ch.95.mo"><title>Repeat of Good Morning Macau</title></programme>
<programme start="20251212095900 +0000" stop="20251212100000 +0000" channel="TDM Entertainment Ch.95.mo"><title>TDM Focus</title></programme>
<programme start="20251212100000 +0000" stop="20251212102500 +0000" channel="TDM Entertainment Ch.95.mo"><title>Dream For Rim S2</title></programme>
<programme start="20251212102500 +0000" stop="20251212120000 +0000" channel="TDM Entertainment Ch.95.mo"><title>The Listener</title></programme>
<programme start="20251212120000 +0000" stop="20251212123000 +0000" channel="TDM Entertainment Ch.95.mo"><title>The Canine Coach III</title></programme>
<programme start="20251212123000 +0000" stop="20251212133000 +0000" channel="TDM Entertainment Ch.95.mo"><title>Appraising Antiques</title></programme>
<programme start="20251212133000 +0000" stop="20251212133500 +0000" channel="TDM Entertainment Ch.95.mo"><title>Mysterious Sichuan, Wonderful Vision</title></programme>
<programme start="20251212133500 +0000" stop="20251212140000 +0000" channel="TDM Entertainment Ch.95.mo"><title>Paradise Kitchen Bali</title></programme>
<programme start="20251212140000 +0000" stop="20251212160100 +0000" channel="TDM Entertainment Ch.95.mo"><title>Movie: The Greatest Lover</title></programme>
<programme start="20251212160100 +0000" stop="20251213015900 +0000" channel="TDM Entertainment Ch.95.mo"><title>Close</title></programme>
<programme start="20251213015900 +0000" stop="20251213020000 +0000" channel="TDM Entertainment Ch.95.mo"><title>Open</title></programme>
<programme start="20251213020000 +0000" stop="20251213080000 +0000" channel="TDM Entertainment Ch.95.mo"><title>(SAME AS “TDM OU MUN”)</title></programme>
<programme start="20251210225900 +0000" stop="20251210230000 +0000" channel="TDM Info Ch.94.mo"><title>Open</title></programme>
<programme start="20251210230000 +0000" stop="20251210235500 +0000" channel="TDM Info Ch.94.mo"><title>TDM Morning News</title></programme>
<programme start="20251210235500 +0000" stop="20251211000000 +0000" channel="TDM Info Ch.94.mo"><title>TDM Focus</title></programme>
<programme start="20251211000000 +0000" stop="20251211010000 +0000" channel="TDM Info Ch.94.mo"><title>Good Morning Macau</title></programme>
<programme start="20251211010000 +0000" stop="20251211013000 +0000" channel="TDM Info Ch.94.mo"><title>TDM Morning News (Repeat)</title></programme>
<programme start="20251211013000 +0000" stop="20251211020000 +0000" channel="TDM Info Ch.94.mo"><title>All About the Greater Bay Area</title></programme>
<programme start="20251211020000 +0000" stop="20251211023000 +0000" channel="TDM Info Ch.94.mo"><title>News Summary</title></programme>
<programme start="20251211023000 +0000" stop="20251211030000 +0000" channel="TDM Info Ch.94.mo"><title>News Summary</title></programme>
<programme start="20251211030000 +0000" stop="20251211031200 +0000" channel="TDM Info Ch.94.mo"><title>News Summary</title></programme>
<programme start="20251211031200 +0000" stop="20251211032000 +0000" channel="TDM Info Ch.94.mo"><title>Hengqin Guide</title></programme>
<programme start="20251211032000 +0000" stop="20251211040000 +0000" channel="TDM Info Ch.94.mo"><title>City News Net of China (Repeat)</title></programme>
<programme start="20251211040000 +0000" stop="20251211041700 +0000" channel="TDM Info Ch.94.mo"><title>News Summary</title></programme>
<programme start="20251211041700 +0000" stop="20251211042500 +0000" channel="TDM Info Ch.94.mo"><title>Hengqin Guide</title></programme>
<programme start="20251211042500 +0000" stop="20251211043000 +0000" channel="TDM Info Ch.94.mo"><title>Food Price Update</title></programme>
<programme start="20251211043000 +0000" stop="20251211050000 +0000" channel="TDM Info Ch.94.mo"><title>All About the Greater Bay Area</title></programme>
<programme start="20251211050000 +0000" stop="20251211051500 +0000" channel="TDM Info Ch.94.mo"><title>News Summary</title></programme>
<programme start="20251211051500 +0000" stop="20251211052800 +0000" channel="TDM Info Ch.94.mo"><title>Hengqin Guide</title></programme>
<programme start="20251211052800 +0000" stop="20251211053000 +0000" channel="TDM Info Ch.94.mo"><title>Noon Weather Report</title></programme>
<programme start="20251211053000 +0000" stop="20251211060000 +0000" channel="TDM Info Ch.94.mo"><title>Noon News</title></programme>
<programme start="20251211060000 +0000" stop="20251211070000 +0000" channel="TDM Info Ch.94.mo"><title>Financial Daily</title></programme>
<programme start="20251211070000 +0000" stop="20251211072500 +0000" channel="TDM Info Ch.94.mo"><title>News Summary</title></programme>
<programme start="20251211072500 +0000" stop="20251211073000 +0000" channel="TDM Info Ch.94.mo"><title>Food Price Update</title></programme>
<programme start="20251211073000 +0000" stop="20251211080000 +0000" channel="TDM Info Ch.94.mo"><title>News Summary</title></programme>
<programme start="20251211080000 +0000" stop="20251211083000 +0000" channel="TDM Info Ch.94.mo"><title>News Summary</title></programme>
<programme start="20251211083000 +0000" stop="20251211090000 +0000" channel="TDM Info Ch.94.mo"><title>News Summary</title></programme>
<programme start="20251211090000 +0000" stop="20251211093000 +0000" channel="TDM Info Ch.94.mo"><title>News Summary</title></programme>
<programme start="20251211093000 +0000" stop="20251211095000 +0000" channel="TDM Info Ch.94.mo"><title>News Summary</title></programme>
<programme start="20251211095000 +0000" stop="20251211100000 +0000" channel="TDM Info Ch.94.mo"><title>Hengqin Guide</title></programme>
<programme start="20251211100000 +0000" stop="20251211100500 +0000" channel="TDM Info Ch.94.mo"><title>News Summary</title></programme>
<programme start="20251211100500 +0000" stop="20251211100600 +0000" channel="TDM Info Ch.94.mo"><title>TDM Focus</title></programme>
<programme start="20251211100600 +0000" stop="20251211103200 +0000" channel="TDM Info Ch.94.mo"><title>Repeat of Good Morning Macau</title></programme>
<programme start="20251211103200 +0000" stop="20251211110000 +0000" channel="TDM Info Ch.94.mo"><title>All About the Greater Bay Area</title></programme>
<programme start="20251211110000 +0000" stop="20251211115500 +0000" channel="TDM Info Ch.94.mo"><title>TDM News</title></programme>
<programme start="20251211115500 +0000" stop="20251211115900 +0000" channel="TDM Info Ch.94.mo"><title>Weather Report</title></programme>
<programme start="20251211115900 +0000" stop="20251211120000 +0000" channel="TDM Info Ch.94.mo"><title>TDM Focus</title></programme>
<programme start="20251211120000 +0000" stop="20251211130000 +0000" channel="TDM Info Ch.94.mo"><title>TDM News (Taped)</title></programme>
<programme start="20251211130000 +0000" stop="20251211140000 +0000" channel="TDM Info Ch.94.mo"><title>TDM News (Taped)</title></programme>
<programme start="20251211140000 +0000" stop="20251211143100 +0000" channel="TDM Info Ch.94.mo"><title>Pu-Tong-Hua News</title></programme>
<programme start="20251211143100 +0000" stop="20251211151500 +0000" channel="TDM Info Ch.94.mo"><title>Wind and Fire</title></programme>
<programme start="20251211151500 +0000" stop="20251211155000 +0000" channel="TDM Info Ch.94.mo"><title>TDM Late News</title></programme>
<programme start="20251211155000 +0000" stop="20251211160500 +0000" channel="TDM Info Ch.94.mo"><title>Sport News</title></programme>
<programme start="20251211160500 +0000" stop="20251211163300 +0000" channel="TDM Info Ch.94.mo"><title>City Report of China</title></programme>
<programme start="20251211163300 +0000" stop="20251211164500 +0000" channel="TDM Info Ch.94.mo"><title>Expatriates in China</title></programme>
<programme start="20251211164500 +0000" stop="20251211171500 +0000" channel="TDM Info Ch.94.mo"><title>Pu-Tong-Hua News (Taped)</title></programme>
<programme start="20251211171500 +0000" stop="20251211175000 +0000" channel="TDM Info Ch.94.mo"><title>TDM Late News (Taped)</title></programme>
<programme start="20251211175000 +0000" stop="20251211180000 +0000" channel="TDM Info Ch.94.mo"><title>Sport News (Repeat)</title></programme>
<programme start="20251211180000 +0000" stop="20251211225900 +0000" channel="TDM Info Ch.94.mo"><title>Close</title></programme>
<programme start="20251211225900 +0000" stop="20251211230000 +0000" channel="TDM Info Ch.94.mo"><title>Open</title></programme>
<programme start="20251211230000 +0000" stop="20251211235500 +0000" channel="TDM Info Ch.94.mo"><title>TDM Morning News</title></programme>
<programme start="20251211235500 +0000" stop="20251212000000 +0000" channel="TDM Info Ch.94.mo"><title>TDM Focus</title></programme>
<programme start="20251212000000 +0000" stop="20251212010000 +0000" channel="TDM Info Ch.94.mo"><title>Good Morning Macau</title></programme>
<programme start="20251212010000 +0000" stop="20251212013000 +0000" channel="TDM Info Ch.94.mo"><title>TDM Morning News (Repeat)</title></programme>
<programme start="20251212013000 +0000" stop="20251212020000 +0000" channel="TDM Info Ch.94.mo"><title>All About the Greater Bay Area</title></programme>
<programme start="20251212020000 +0000" stop="20251212023000 +0000" channel="TDM Info Ch.94.mo"><title>News Summary</title></programme>
<programme start="20251212023000 +0000" stop="20251212030000 +0000" channel="TDM Info Ch.94.mo"><title>News Summary</title></programme>
<programme start="20251212030000 +0000" stop="20251212031500 +0000" channel="TDM Info Ch.94.mo"><title>News Summary</title></programme>
<programme start="20251212031500 +0000" stop="20251212032000 +0000" channel="TDM Info Ch.94.mo"><title>Focus China</title></programme>
<programme start="20251212032000 +0000" stop="20251212040000 +0000" channel="TDM Info Ch.94.mo"><title>Wind and Fire (Repeat)</title></programme>
<programme start="20251212040000 +0000" stop="20251212042000 +0000" channel="TDM Info Ch.94.mo"><title>News Summary</title></programme>
<programme start="20251212042000 +0000" stop="20251212042500 +0000" channel="TDM Info Ch.94.mo"><title>Focus China</title></programme>
<programme start="20251212042500 +0000" stop="20251212043000 +0000" channel="TDM Info Ch.94.mo"><title>Food Price Update</title></programme>
<programme start="20251212043000 +0000" stop="20251212050000 +0000" channel="TDM Info Ch.94.mo"><title>All About the Greater Bay Area</title></programme>
<programme start="20251212050000 +0000" stop="20251212052300 +0000" channel="TDM Info Ch.94.mo"><title>News Summary</title></programme>
<programme start="20251212052300 +0000" stop="20251212052800 +0000" channel="TDM Info Ch.94.mo"><title>Focus China</title></programme>
<programme start="20251212052800 +0000" stop="20251212053000 +0000" channel="TDM Info Ch.94.mo"><title>Noon Weather Report</title></programme>
<programme start="20251212053000 +0000" stop="20251212060000 +0000" channel="TDM Info Ch.94.mo"><title>Noon News</title></programme>
<programme start="20251212060000 +0000" stop="20251212070000 +0000" channel="TDM Info Ch.94.mo"><title>Financial Daily</title></programme>
<programme start="20251212070000 +0000" stop="20251212072500 +0000" channel="TDM Info Ch.94.mo"><title>News Summary</title></programme>
<programme start="20251212072500 +0000" stop="20251212073000 +0000" channel="TDM Info Ch.94.mo"><title>Food Price Update</title></programme>
<programme start="20251212073000 +0000" stop="20251212080000 +0000" channel="TDM Info Ch.94.mo"><title>News Summary</title></programme>
<programme start="20251212080000 +0000" stop="20251212083000 +0000" channel="TDM Info Ch.94.mo"><title>News Summary</title></programme>
<programme start="20251212083000 +0000" stop="20251212090000 +0000" channel="TDM Info Ch.94.mo"><title>News Summary</title></programme>
<programme start="20251212090000 +0000" stop="20251212093000 +0000" channel="TDM Info Ch.94.mo"><title>News Summary</title></programme>
<programme start="20251212093000 +0000" stop="20251212095500 +0000" channel="TDM Info Ch.94.mo"><title>News Summary</title></programme>
<programme start="20251212095500 +0000" stop="20251212100000 +0000" channel="TDM Info Ch.94.mo"><title>Focus China</title></programme>
<programme start="20251212100000 +0000" stop="20251212100500 +0000" channel="TDM Info Ch.94.mo"><title>News Summary</title></programme>
<programme start="20251212100500 +0000" stop="20251212100600 +0000" channel="TDM Info Ch.94.mo"><title>TDM Focus</title></programme>
<programme start="20251212100600 +0000" stop="20251212103200 +0000" channel="TDM Info Ch.94.mo"><title>Repeat of Good Morning Macau</title></programme>
<programme start="20251212103200 +0000" stop="20251212110000 +0000" channel="TDM Info Ch.94.mo"><title>All About the Greater Bay Area</title></programme>
<programme start="20251212110000 +0000" stop="20251212115500 +0000" channel="TDM Info Ch.94.mo"><title>TDM News</title></programme>
<programme start="20251212115500 +0000" stop="20251212115900 +0000" channel="TDM Info Ch.94.mo"><title>Weather Report</title></programme>
<programme start="20251212115900 +0000" stop="20251212120000 +0000" channel="TDM Info Ch.94.mo"><title>TDM Focus</title></programme>
<programme start="20251212120000 +0000" stop="20251212130000 +0000" channel="TDM Info Ch.94.mo"><title>TDM News (Taped)</title></programme>
<programme start="20251212130000 +0000" stop="20251212140000 +0000" channel="TDM Info Ch.94.mo"><title>TDM News (Taped)</title></programme>
<programme start="20251212140000 +0000" stop="20251212143100 +0000" channel="TDM Info Ch.94.mo"><title>Pu-Tong-Hua News</title></programme>
<programme start="20251212143100 +0000" stop="20251212150200 +0000" channel="TDM Info Ch.94.mo"><title>Macau News File</title></programme>
<programme start="20251212150200 +0000" stop="20251212151500 +0000" channel="TDM Info Ch.94.mo"><title>Patrimonio Cultural Intangível de Macau</title></programme>
<programme start="20251212151500 +0000" stop="20251212155000 +0000" channel="TDM Info Ch.94.mo"><title>TDM Late News</title></programme>
<programme start="20251212155000 +0000" stop="20251212160500 +0000" channel="TDM Info Ch.94.mo"><title>Sport News</title></programme>
<programme start="20251212160500 +0000" stop="20251212163500 +0000" channel="TDM Info Ch.94.mo"><title>City Report of China</title></programme>
<programme start="20251212163500 +0000" stop="20251212164500 +0000" channel="TDM Info Ch.94.mo"><title>Expatriates in China</title></programme>
<programme start="20251212164500 +0000" stop="20251212171500 +0000" channel="TDM Info Ch.94.mo"><title>Pu-Tong-Hua News (Taped)</title></programme>
<programme start="20251212171500 +0000" stop="20251212175000 +0000" channel="TDM Info Ch.94.mo"><title>TDM Late News (Taped)</title></programme>
<programme start="20251212175000 +0000" stop="20251212180000 +0000" channel="TDM Info Ch.94.mo"><title>Sport News (Repeat)</title></programme>
<programme start="20251212180000 +0000" stop="20251212225900 +0000" channel="TDM Info Ch.94.mo"><title>Close</title></programme>
<programme start="20251212225900 +0000" stop="20251212230000 +0000" channel="TDM Info Ch.94.mo"><title>Open</title></programme>
<programme start="20251212230000 +0000" stop="20251212235500 +0000" channel="TDM Info Ch.94.mo"><title>TDM Morning News</title></programme>
<programme start="20251212235500 +0000" stop="20251213000000 +0000" channel="TDM Info Ch.94.mo"><title>TDM Focus</title></programme>
<programme start="20251213000000 +0000" stop="20251213010000 +0000" channel="TDM Info Ch.94.mo"><title>Good Morning Macau</title></programme>
<programme start="20251213010000 +0000" stop="20251213013000 +0000" channel="TDM Info Ch.94.mo"><title>TDM Morning News (Repeat)</title></programme>
<programme start="20251213013000 +0000" stop="20251213015500 +0000" channel="TDM Info Ch.94.mo"><title>Learning the Cello</title></programme>
<programme start="20251213015500 +0000" stop="20251213020000 +0000" channel="TDM Info Ch.94.mo"><title>Good Morning Macau : Highlights</title></programme>
<programme start="20251213020000 +0000" stop="20251213023000 +0000" channel="TDM Info Ch.94.mo"><title>News Summary</title></programme>
<programme start="20251213023000 +0000" stop="20251213030000 +0000" channel="TDM Info Ch.94.mo"><title>News Summary</title></programme>
<programme start="20251213030000 +0000" stop="20251213031000 +0000" channel="TDM Info Ch.94.mo"><title>News Summary</title></programme>
<programme start="20251213031000 +0000" stop="20251213031500 +0000" channel="TDM Info Ch.94.mo"><title>Overview of The Current Affairs</title></programme>
<programme start="20251213031500 +0000" stop="20251213032000 +0000" channel="TDM Info Ch.94.mo"><title>China Soft Power</title></programme>
<programme start="20251213032000 +0000" stop="20251213035500 +0000" channel="TDM Info Ch.94.mo"><title>Macau News File (Repeat)</title></programme>
<programme start="20251210230000 +0000" stop="20251210235500 +0000" channel="TDM Ou Mun Ch. 91.mo"><title>TDM Morning News</title></programme>
<programme start="20251210235500 +0000" stop="20251211000000 +0000" channel="TDM Ou Mun Ch. 91.mo"><title>TDM Focus</title></programme>
<programme start="20251211000000 +0000" stop="20251211010000 +0000" channel="TDM Ou Mun Ch. 91.mo"><title>Good Morning Macau</title></programme>
<programme start="20251211010000 +0000" stop="20251211010500 +0000" channel="TDM Ou Mun Ch. 91.mo"><title>Having Fun in Tang Poetry</title></programme>
<programme start="20251211010500 +0000" stop="20251211012500 +0000" channel="TDM Ou Mun Ch. 91.mo"><title>Our People, Our Life</title></programme>
<programme start="20251211012500 +0000" stop="20251211020000 +0000" channel="TDM Ou Mun Ch. 91.mo"><title>Overseas Chinese Against the Japanese Invasion of China</title></programme>
<programme start="20251211020000 +0000" stop="20251211023000 +0000" channel="TDM Ou Mun Ch. 91.mo"><title>News Summary</title></programme>
<programme start="20251211023000 +0000" stop="20251211031000 +0000" channel="TDM Ou Mun Ch. 91.mo"><title>Treasures of Ancient Shu</title></programme>
<programme start="20251211031000 +0000" stop="20251211033000 +0000" channel="TDM Ou Mun Ch. 91.mo"><title>Our People, Our Life</title></programme>
<programme start="20251211033000 +0000" stop="20251211040000 +0000" channel="TDM Ou Mun Ch. 91.mo"><title>All About the Greater Bay Area</title></programme>
<programme start="20251211040000 +0000" stop="20251211045000 +0000" channel="TDM Ou Mun Ch. 91.mo"><title>The Fearless</title></programme>
<programme start="20251211045000 +0000" stop="20251211050000 +0000" channel="TDM Ou Mun Ch. 91.mo"><title>My Land, My People</title></programme>
<programme start="20251211050000 +0000" stop="20251211050500 +0000" channel="TDM Ou Mun Ch. 91.mo"><title>Noon Weather Report</title></programme>
<programme start="20251211050500 +0000" stop="20251211051500 +0000" channel="TDM Ou Mun Ch. 91.mo"><title>Hengqin Guide</title></programme>
<programme start="20251211051500 +0000" stop="20251211052000 +0000" channel="TDM Ou Mun Ch. 91.mo"><title>Good Morning Macau : Highlights</title></programme>
<programme start="20251211052000 +0000" stop="20251211052500 +0000" channel="TDM Ou Mun Ch. 91.mo"><title>"You Ask, We Answer" Guangdong-Macao Laws Livestream</title></programme>
<programme start="20251211052500 +0000" stop="20251211053000 +0000" channel="TDM Ou Mun Ch. 91.mo"><title>TDM Focus</title></programme>
<programme start="20251211053000 +0000" stop="20251211060000 +0000" channel="TDM Ou Mun Ch. 91.mo"><title>Noon News</title></programme>
<programme start="20251211060000 +0000" stop="20251211070000 +0000" channel="TDM Ou Mun Ch. 91.mo"><title>Financial Daily</title></programme>
<programme start="20251211070000 +0000" stop="20251211074000 +0000" channel="TDM Ou Mun Ch. 91.mo"><title>City News Net of China (Repeat)</title></programme>
<programme start="20251211074000 +0000" stop="20251211080000 +0000" channel="TDM Ou Mun Ch. 91.mo"><title>Our People, Our Life</title></programme>
<programme start="20251211080000 +0000" stop="20251211082500 +0000" channel="TDM Ou Mun Ch. 91.mo"><title>Repeat of Good Morning Macau</title></programme>
<programme start="20251211082500 +0000" stop="20251211084500 +0000" channel="TDM Ou Mun Ch. 91.mo"><title>Children Programme: Space Protectors (S2)</title></programme>
<programme start="20251211084500 +0000" stop="20251211085600 +0000" channel="TDM Ou Mun Ch. 91.mo"><title>Children Programme: Clangers</title></programme>
<programme start="20251211085600 +0000" stop="20251211090000 +0000" channel="TDM Ou Mun Ch. 91.mo"><title>Having Fun in Tang Poetry</title></programme>
<programme start="20251211090000 +0000" stop="20251211095000 +0000" channel="TDM Ou Mun Ch. 91.mo"><title>Children Programme: Hi-speed Rail Warriors</title></programme>
<programme start="20251211095000 +0000" stop="20251211100000 +0000" channel="TDM Ou Mun Ch. 91.mo"><title>Good Morning Macau : Highlights</title></programme>
<programme start="20251211100000 +0000" stop="20251211100500 +0000" channel="TDM Ou Mun Ch. 91.mo"><title>News Summary</title></programme>
<programme start="20251211100500 +0000" stop="20251211105500 +0000" channel="TDM Ou Mun Ch. 91.mo"><title>Educaçao E Juventude Dinamica (Repeat)</title></programme>
<programme start="20251211105500 +0000" stop="20251211110000 +0000" channel="TDM Ou Mun Ch. 91.mo"><title>TDM Focus</title></programme>
<programme start="20251211110000 +0000" stop="20251211115500 +0000" channel="TDM Ou Mun Ch. 91.mo"><title>TDM News</title></programme>
<programme start="20251211115500 +0000" stop="20251211120000 +0000" channel="TDM Ou Mun Ch. 91.mo"><title>Weather Report</title></programme>
<programme start="20251211120000 +0000" stop="20251211125000 +0000" channel="TDM Ou Mun Ch. 91.mo"><title>The Fearless</title></programme>
<programme start="20251211125000 +0000" stop="20251211130000 +0000" channel="TDM Ou Mun Ch. 91.mo"><title>My Land, My People</title></programme>
<programme start="20251211130000 +0000" stop="20251211132500 +0000" channel="TDM Ou Mun Ch. 91.mo"><title>Our People, Our Life</title></programme>
<programme start="20251211132500 +0000" stop="20251211134700 +0000" channel="TDM Ou Mun Ch. 91.mo"><title>City Foragers</title></programme>
<programme start="20251211134700 +0000" stop="20251211140000 +0000" channel="TDM Ou Mun Ch. 91.mo"><title>Good Morning Macau : Highlights</title></programme>
<programme start="20251211140000 +0000" stop="20251211143000 +0000" channel="TDM Ou Mun Ch. 91.mo"><title>Pu-Tong-Hua News</title></programme>
<programme start="20251211143000 +0000" stop="20251211151500 +0000" channel="TDM Ou Mun Ch. 91.mo"><title>22:30 TDM Info - Express: Wind and Fire</title></programme>
<programme start="20251211151500 +0000" stop="20251211155000 +0000" channel="TDM Ou Mun Ch. 91.mo"><title>TDM Late News</title></programme>
<programme start="20251211155000 +0000" stop="20251211160100 +0000" channel="TDM Ou Mun Ch. 91.mo"><title>Sport News</title></programme>
<programme start="20251211160100 +0000" stop="20251211163000 +0000" channel="TDM Ou Mun Ch. 91.mo"><title>All About the Greater Bay Area</title></programme>
<programme start="20251211163000 +0000" stop="20251211165200 +0000" channel="TDM Ou Mun Ch. 91.mo"><title>City Foragers</title></programme>
<programme start="20251211165200 +0000" stop="20251211170000 +0000" channel="TDM Ou Mun Ch. 91.mo"><title>Patrimonio Cultural Intangível de Macau</title></programme>
<programme start="20251211170000 +0000" stop="20251211175100 +0000" channel="TDM Ou Mun Ch. 91.mo"><title>The Fearless</title></programme>
<programme start="20251211175100 +0000" stop="20251211180000 +0000" channel="TDM Ou Mun Ch. 91.mo"><title>Having Fun in Tang Poetry</title></programme>
<programme start="20251211180000 +0000" stop="20251211182300 +0000" channel="TDM Ou Mun Ch. 91.mo"><title>Repeat of Good Morning Macau</title></programme>
<programme start="20251211182300 +0000" stop="20251211183000 +0000" channel="TDM Ou Mun Ch. 91.mo"><title>World Heritage Sites</title></programme>
<programme start="20251211183000 +0000" stop="20251211190000 +0000" channel="TDM Ou Mun Ch. 91.mo"><title>Pu-Tong-Hua News</title></programme>
<programme start="20251211190000 +0000" stop="20251211193500 +0000" channel="TDM Ou Mun Ch. 91.mo"><title>TDM Late News</title></programme>
<programme start="20251211193500 +0000" stop="20251211201500 +0000" channel="TDM Ou Mun Ch. 91.mo"><title>Wind and Fire (Repeat)</title></programme>
<programme start="20251211201500 +0000" stop="20251211203500 +0000" channel="TDM Ou Mun Ch. 91.mo"><title>Our People, Our Life</title></programme>
<programme start="20251211203500 +0000" stop="20251211210100 +0000" channel="TDM Ou Mun Ch. 91.mo"><title>All About the Greater Bay Area</title></programme>
<programme start="20251211210100 +0000" stop="20251211213000 +0000" channel="TDM Ou Mun Ch. 91.mo"><title>#Hipsters Choice</title></programme>
<programme start="20251211213000 +0000" stop="20251211215300 +0000" channel="TDM Ou Mun Ch. 91.mo"><title>Repeat of Good Morning Macau</title></programme>
<programme start="20251211215300 +0000" stop="20251211220000 +0000" channel="TDM Ou Mun Ch. 91.mo"><title>World Heritage Sites</title></programme>
<programme start="20251211220000 +0000" stop="20251211224000 +0000" channel="TDM Ou Mun Ch. 91.mo"><title>Wind and Fire (Repeat)</title></programme>
<programme start="20251211224000 +0000" stop="20251211230000 +0000" channel="TDM Ou Mun Ch. 91.mo"><title>Our People, Our Life</title></programme>
<programme start="20251211230000 +0000" stop="20251211235500 +0000" channel="TDM Ou Mun Ch. 91.mo"><title>TDM Morning News</title></programme>
<programme start="20251211235500 +0000" stop="20251212000000 +0000" channel="TDM Ou Mun Ch. 91.mo"><title>TDM Focus</title></programme>
<programme start="20251212000000 +0000" stop="20251212010000 +0000" channel="TDM Ou Mun Ch. 91.mo"><title>Good Morning Macau</title></programme>
<programme start="20251212010000 +0000" stop="20251212010500 +0000" channel="TDM Ou Mun Ch. 91.mo"><title>Having Fun in Tang Poetry</title></programme>
<programme start="20251212010500 +0000" stop="20251212012500 +0000" channel="TDM Ou Mun Ch. 91.mo"><title>Our People, Our Life</title></programme>
<programme start="20251212012500 +0000" stop="20251212015000 +0000" channel="TDM Ou Mun Ch. 91.mo"><title>City Foragers</title></programme>
<programme start="20251212015000 +0000" stop="20251212020000 +0000" channel="TDM Ou Mun Ch. 91.mo"><title>World Heritage Sites</title></programme>
<programme start="20251212020000 +0000" stop="20251212023000 +0000" channel="TDM Ou Mun Ch. 91.mo"><title>News Summary</title></programme>
<programme start="20251212023000 +0000" stop="20251212031000 +0000" channel="TDM Ou Mun Ch. 91.mo"><title>Wind and Fire (Repeat)</title></programme>
<programme start="20251212031000 +0000" stop="20251212033000 +0000" channel="TDM Ou Mun Ch. 91.mo"><title>Our People, Our Life</title></programme>
<programme start="20251212033000 +0000" stop="20251212040000 +0000" channel="TDM Ou Mun Ch. 91.mo"><title>All About the Greater Bay Area</title></programme>
<programme start="20251212040000 +0000" stop="20251212045000 +0000" channel="TDM Ou Mun Ch. 91.mo"><title>The Fearless</title></programme>
<programme start="20251212045000 +0000" stop="20251212050000 +0000" channel="TDM Ou Mun Ch. 91.mo"><title>My Land, My People</title></programme>
<programme start="20251212050000 +0000" stop="20251212050500 +0000" channel="TDM Ou Mun Ch. 91.mo"><title>Noon Weather Report</title></programme>
<programme start="20251212050500 +0000" stop="20251212051500 +0000" channel="TDM Ou Mun Ch. 91.mo"><title>Focus China</title></programme>
<programme start="20251212051500 +0000" stop="20251212052000 +0000" channel="TDM Ou Mun Ch. 91.mo"><title>Good Morning Macau : Highlights</title></programme>
<programme start="20251212052000 +0000" stop="20251212052500 +0000" channel="TDM Ou Mun Ch. 91.mo"><title>Having Fun in Tang Poetry</title></programme>
<programme start="20251212052500 +0000" stop="20251212053000 +0000" channel="TDM Ou Mun Ch. 91.mo"><title>TDM Focus</title></programme>
<programme start="20251212053000 +0000" stop="20251212060000 +0000" channel="TDM Ou Mun Ch. 91.mo"><title>Noon News</title></programme>
<programme start="20251212060000 +0000" stop="20251212070000 +0000" channel="TDM Ou Mun Ch. 91.mo"><title>Financial Daily</title></programme>
<programme start="20251212070000 +0000" stop="20251212074000 +0000" channel="TDM Ou Mun Ch. 91.mo"><title>Wind and Fire (Repeat)</title></programme>
<programme start="20251212074000 +0000" stop="20251212080000 +0000" channel="TDM Ou Mun Ch. 91.mo"><title>Our People, Our Life</title></programme>
<programme start="20251212080000 +0000" stop="20251212082500 +0000" channel="TDM Ou Mun Ch. 91.mo"><title>Repeat of Good Morning Macau</title></programme>
<programme start="20251212082500 +0000" stop="20251212084000 +0000" channel="TDM Ou Mun Ch. 91.mo"><title>Children Programme: Space Protectors (S2)</title></programme>
<programme start="20251212084000 +0000" stop="20251212085500 +0000" channel="TDM Ou Mun Ch. 91.mo"><title>Children Programme: The Brave City : Legend of Mystical Beasts</title></programme>
<programme start="20251212085500 +0000" stop="20251212090000 +0000" channel="TDM Ou Mun Ch. 91.mo"><title>Having Fun in Tang Poetry</title></programme>
<programme start="20251212090000 +0000" stop="20251212095000 +0000" channel="TDM Ou Mun Ch. 91.mo"><title>Children Programme: Hi-speed Rail Warriors</title></programme>
<programme start="20251212095000 +0000" stop="20251212100000 +0000" channel="TDM Ou Mun Ch. 91.mo"><title>Good Morning Macau : Highlights</title></programme>
<programme start="20251212100000 +0000" stop="20251212100500 +0000" channel="TDM Ou Mun Ch. 91.mo"><title>News Summary</title></programme>
<programme start="20251212100500 +0000" stop="20251212105500 +0000" channel="TDM Ou Mun Ch. 91.mo"><title>Educaçao E Juventude Dinamica</title></programme>
<programme start="20251212105500 +0000" stop="20251212110000 +0000" channel="TDM Ou Mun Ch. 91.mo"><title>TDM Focus</title></programme>
<programme start="20251212110000 +0000" stop="20251212115500 +0000" channel="TDM Ou Mun Ch. 91.mo"><title>TDM News</title></programme>
<programme start="20251212115500 +0000" stop="20251212120000 +0000" channel="TDM Ou Mun Ch. 91.mo"><title>Weather Report</title></programme>
<programme start="20251212120000 +0000" stop="20251212125000 +0000" channel="TDM Ou Mun Ch. 91.mo"><title>The Fearless</title></programme>
<programme start="20251212125000 +0000" stop="20251212130000 +0000" channel="TDM Ou Mun Ch. 91.mo"><title>My Land, My People</title></programme>
<programme start="20251212130000 +0000" stop="20251212131900 +0000" channel="TDM Ou Mun Ch. 91.mo"><title>Macau Chat Room</title></programme>
<programme start="20251212131900 +0000" stop="20251212132500 +0000" channel="TDM Ou Mun Ch. 91.mo"><title>Expatriates in China</title></programme>
<programme start="20251212132500 +0000" stop="20251212135200 +0000" channel="TDM Ou Mun Ch. 91.mo"><title>Health Hacks</title></programme>
<programme start="20251212135200 +0000" stop="20251212140000 +0000" channel="TDM Ou Mun Ch. 91.mo"><title>Good Morning Macau : Highlights</title></programme>
<programme start="20251212140000 +0000" stop="20251212143000 +0000" channel="TDM Ou Mun Ch. 91.mo"><title>Pu-Tong-Hua News</title></programme>
<programme start="20251212143000 +0000" stop="20251212150500 +0000" channel="TDM Ou Mun Ch. 91.mo"><title>22:30 TDM Info - Express: Macau News File</title></programme>
<programme start="20251212150500 +0000" stop="20251212151500 +0000" channel="TDM Ou Mun Ch. 91.mo"><title>Patrimonio Cultural Intangível de Macau</title></programme>
<programme start="20251212151500 +0000" stop="20251212155000 +0000" channel="TDM Ou Mun Ch. 91.mo"><title>TDM Late News</title></programme>
<programme start="20251212155000 +0000" stop="20251212160100 +0000" channel="TDM Ou Mun Ch. 91.mo"><title>Sport News</title></programme>
<programme start="20251212160100 +0000" stop="20251212163000 +0000" channel="TDM Ou Mun Ch. 91.mo"><title>All About the Greater Bay Area</title></programme>
<programme start="20251212163000 +0000" stop="20251212170000 +0000" channel="TDM Ou Mun Ch. 91.mo"><title>Health Hacks</title></programme>
<programme start="20251212170000 +0000" stop="20251212175000 +0000" channel="TDM Ou Mun Ch. 91.mo"><title>The Fearless</title></programme>
<programme start="20251212175000 +0000" stop="20251212180000 +0000" channel="TDM Ou Mun Ch. 91.mo"><title>Having Fun in Tang Poetry</title></programme>
<programme start="20251212180000 +0000" stop="20251212182300 +0000" channel="TDM Ou Mun Ch. 91.mo"><title>Repeat of Good Morning Macau</title></programme>
<programme start="20251212182300 +0000" stop="20251212183000 +0000" channel="TDM Ou Mun Ch. 91.mo"><title>World Heritage Sites</title></programme>
<programme start="20251212183000 +0000" stop="20251212190000 +0000" channel="TDM Ou Mun Ch. 91.mo"><title>Pu-Tong-Hua News</title></programme>
<programme start="20251212190000 +0000" stop="20251212193500 +0000" channel="TDM Ou Mun Ch. 91.mo"><title>TDM Late News</title></programme>
<programme start="20251212193500 +0000" stop="20251212201000 +0000" channel="TDM Ou Mun Ch. 91.mo"><title>Macau News File (Repeat)</title></programme>
<programme start="20251212201000 +0000" stop="20251212201500 +0000" channel="TDM Ou Mun Ch. 91.mo"><title>Patrimonio Cultural Intangível de Macau</title></programme>
<programme start="20251212201500 +0000" stop="20251212203500 +0000" channel="TDM Ou Mun Ch. 91.mo"><title>Our People, Our Life</title></programme>
<programme start="20251212203500 +0000" stop="20251212210100 +0000" channel="TDM Ou Mun Ch. 91.mo"><title>All About the Greater Bay Area</title></programme>
<programme start="20251212210100 +0000" stop="20251212212600 +0000" channel="TDM Ou Mun Ch. 91.mo"><title>#Hipsters Choice</title></programme>
<programme start="20251212212600 +0000" stop="20251212215000 +0000" channel="TDM Ou Mun Ch. 91.mo"><title>Repeat of Good Morning Macau</title></programme>
<programme start="20251212215000 +0000" stop="20251212220000 +0000" channel="TDM Ou Mun Ch. 91.mo"><title>World Heritage Sites</title></programme>
<programme start="20251212220000 +0000" stop="20251212223500 +0000" channel="TDM Ou Mun Ch. 91.mo"><title>Macau News File (Repeat)</title></programme>
<programme start="20251212223500 +0000" stop="20251212224000 +0000" channel="TDM Ou Mun Ch. 91.mo"><title>Patrimonio Cultural Intangível de Macau</title></programme>
<programme start="20251212224000 +0000" stop="20251212230000 +0000" channel="TDM Ou Mun Ch. 91.mo"><title>Our People, Our Life</title></programme>
<programme start="20251212230000 +0000" stop="20251212235500 +0000" channel="TDM Ou Mun Ch. 91.mo"><title>TDM Morning News</title></programme>
<programme start="20251212235500 +0000" stop="20251213000000 +0000" channel="TDM Ou Mun Ch. 91.mo"><title>TDM Focus</title></programme>
<programme start="20251213000000 +0000" stop="20251213010000 +0000" channel="TDM Ou Mun Ch. 91.mo"><title>Good Morning Macau</title></programme>
<programme start="20251213010000 +0000" stop="20251213010500 +0000" channel="TDM Ou Mun Ch. 91.mo"><title>Having Fun in Tang Poetry</title></programme>
<programme start="20251213010500 +0000" stop="20251213012000 +0000" channel="TDM Ou Mun Ch. 91.mo"><title>Macau Chat Room</title></programme>
<programme start="20251213012000 +0000" stop="20251213013000 +0000" channel="TDM Ou Mun Ch. 91.mo"><title>Expatriates in China</title></programme>
<programme start="20251213013000 +0000" stop="20251213020000 +0000" channel="TDM Ou Mun Ch. 91.mo"><title>Health Hacks</title></programme>
<programme start="20251213020000 +0000" stop="20251213023000 +0000" channel="TDM Ou Mun Ch. 91.mo"><title>News Summary</title></programme>
<programme start="20251213023000 +0000" stop="20251213030500 +0000" channel="TDM Ou Mun Ch. 91.mo"><title>Macau News File (Repeat)</title></programme>
<programme start="20251213030500 +0000" stop="20251213031000 +0000" channel="TDM Ou Mun Ch. 91.mo"><title>Patrimonio Cultural Intangível de Macau</title></programme>
<programme start="20251213031000 +0000" stop="20251213033000 +0000" channel="TDM Ou Mun Ch. 91.mo"><title>Our People, Our Life</title></programme>
<programme start="20251211015900 +0000" stop="20251211020000 +0000" channel="TDM Sport Ch.93.mo"><title>Open</title></programme>
<programme start="20251211020000 +0000" stop="20251211040500 +0000" channel="TDM Sport Ch.93.mo"><title>2025 US Open Tennis Championships (Edited Version) : Mens Singles Quarter final</title></programme>
<programme start="20251211040500 +0000" stop="20251211050000 +0000" channel="TDM Sport Ch.93.mo"><title>BWF World Tour - India Open 2025 : Womens Single - Final</title></programme>
<programme start="20251211050000 +0000" stop="20251211051500 +0000" channel="TDM Sport Ch.93.mo"><title>Sport News</title></programme>
<programme start="20251211051500 +0000" stop="20251211054500 +0000" channel="TDM Sport Ch.93.mo"><title>2025 Michelin Le Mans Cup Magazine: ep 5. Silverstone</title></programme>
<programme start="20251211054500 +0000" stop="20251211060000 +0000" channel="TDM Sport Ch.93.mo"><title>The Encyclopedia Of Classic Cars (Edited version)</title></programme>
<programme start="20251211060000 +0000" stop="20251211080000 +0000" channel="TDM Sport Ch.93.mo"><title>The 12th National Paralympic Games and the 9th Special Olympics (Live)</title></programme>
<programme start="20251211080000 +0000" stop="20251211084000 +0000" channel="TDM Sport Ch.93.mo"><title>Macau Sports 2025</title></programme>
<programme start="20251211084000 +0000" stop="20251211094500 +0000" channel="TDM Sport Ch.93.mo"><title>BWF World Tour - India Open 2025 : Mens Double - Final</title></programme>
<programme start="20251211094500 +0000" stop="20251211095500 +0000" channel="TDM Sport Ch.93.mo"><title>Slowstep Yore</title></programme>
<programme start="20251211095500 +0000" stop="20251211120000 +0000" channel="TDM Sport Ch.93.mo"><title>AFC Champions League Two 2025/26 : Gamba Osaka vs Ratchaburi (Live)</title></programme>
<programme start="20251211120000 +0000" stop="20251211121000 +0000" channel="TDM Sport Ch.93.mo"><title>Sports Weekly Highlight</title></programme>
<programme start="20251211121000 +0000" stop="20251211130500 +0000" channel="TDM Sport Ch.93.mo"><title>AFC Champions League Two 2025/26 : Beijing FC vs Macarthur FC (Live)</title></programme>
<programme start="20251211130500 +0000" stop="20251211131000 +0000" channel="TDM Sport Ch.93.mo"><title>Sport News</title></programme>
<programme start="20251211131000 +0000" stop="20251211141500 +0000" channel="TDM Sport Ch.93.mo"><title>AFC Champions League Two 2025/26 : Beijing FC vs Macarthur FC (Live)</title></programme>
<programme start="20251211141500 +0000" stop="20251211143000 +0000" channel="TDM Sport Ch.93.mo"><title>Slowstep Yore</title></programme>
<programme start="20251211143000 +0000" stop="20251211152000 +0000" channel="TDM Sport Ch.93.mo"><title>UEFA Champions League 2025/2026 Highlights</title></programme>
<programme start="20251211152000 +0000" stop="20251211153000 +0000" channel="TDM Sport Ch.93.mo"><title>Sport News</title></programme>
<programme start="20251211153000 +0000" stop="20251211173000 +0000" channel="TDM Sport Ch.93.mo"><title>UEFA Champions League 2025/2026: Club Brugge vs Arsenal (Taped)</title></programme>
<programme start="20251211173000 +0000" stop="20251211174000 +0000" channel="TDM Sport Ch.93.mo"><title>The Encyclopedia Of Classic Cars (Edited version)</title></programme>
<programme start="20251211174000 +0000" stop="20251211194500 +0000" channel="TDM Sport Ch.93.mo"><title>UEFA Europa League 2025/2026 : Utrecht vs Nottingham Forest (Live)</title></programme>
<programme start="20251211194500 +0000" stop="20251211195500 +0000" channel="TDM Sport Ch.93.mo"><title>The Encyclopedia Of Classic Cars (Edited version)</title></programme>
<programme start="20251211195500 +0000" stop="20251211220000 +0000" channel="TDM Sport Ch.93.mo"><title>UEFA Europa League 2025/2026 : Celtic vs Roma (Live)</title></programme>
<programme start="20251211220000 +0000" stop="20251212015900 +0000" channel="TDM Sport Ch.93.mo"><title>Close</title></programme>
<programme start="20251212015900 +0000" stop="20251212020000 +0000" channel="TDM Sport Ch.93.mo"><title>Open</title></programme>
<programme start="20251212020000 +0000" stop="20251212034500 +0000" channel="TDM Sport Ch.93.mo"><title>2025 US Open Tennis Championships (Edited Version) : Womens Doubles Final</title></programme>
<programme start="20251212034500 +0000" stop="20251212040000 +0000" channel="TDM Sport Ch.93.mo"><title>Sports Weekly Highlight</title></programme>
<programme start="20251212040000 +0000" stop="20251212045000 +0000" channel="TDM Sport Ch.93.mo"><title>BWF World Tour - India Open 2025 : Mens Single - Final</title></programme>
<programme start="20251212045000 +0000" stop="20251212050000 +0000" channel="TDM Sport Ch.93.mo"><title>The Encyclopedia Of Classic Cars (Edited version)</title></programme>
<programme start="20251212050000 +0000" stop="20251212051500 +0000" channel="TDM Sport Ch.93.mo"><title>Sport News</title></programme>
<programme start="20251212051500 +0000" stop="20251212054500 +0000" channel="TDM Sport Ch.93.mo"><title>FIBA 3x3 Asia Cup 2025 : Philippines vs Macau (Edited Version)</title></programme>
<programme start="20251212054500 +0000" stop="20251212060000 +0000" channel="TDM Sport Ch.93.mo"><title>Slowstep Yore</title></programme>
<programme start="20251212060000 +0000" stop="20251212080000 +0000" channel="TDM Sport Ch.93.mo"><title>The 12th National Paralympic Games and the 9th Special Olympics (Live)</title></programme>
<programme start="20251212080000 +0000" stop="20251212083000 +0000" channel="TDM Sport Ch.93.mo"><title>FIBA 3x3 Asia Cup 2025 : Turkmenistan vs Macau (Edited Version)</title></programme>
<programme start="20251212083000 +0000" stop="20251212102000 +0000" channel="TDM Sport Ch.93.mo"><title>East Asia Super League 2025-26 Season : Meralco Bolts vs Macau Black</title></programme>
<programme start="20251212102000 +0000" stop="20251212110000 +0000" channel="TDM Sport Ch.93.mo"><title>Global Sports</title></programme>
<programme start="20251212110000 +0000" stop="20251212114500 +0000" channel="TDM Sport Ch.93.mo"><title>La Liga 2025/2026 Highlights</title></programme>
<programme start="20251212114500 +0000" stop="20251212115500 +0000" channel="TDM Sport Ch.93.mo"><title>Sports Weekly Highlight</title></programme>
<programme start="20251212115500 +0000" stop="20251212120000 +0000" channel="TDM Sport Ch.93.mo"><title>The Encyclopedia Of Classic Cars (Edited version)</title></programme>
<programme start="20251212120000 +0000" stop="20251212130000 +0000" channel="TDM Sport Ch.93.mo"><title>UEFA Europa League 2025/2026 : Midtjylland vs Genk (Taped)</title></programme>
<programme start="20251212130000 +0000" stop="20251212130500 +0000" channel="TDM Sport Ch.93.mo"><title>Sport News</title></programme>
<programme start="20251212130500 +0000" stop="20251212140000 +0000" channel="TDM Sport Ch.93.mo"><title>UEFA Europa League 2025/2026 : Midtjylland vs Genk (Taped)</title></programme>
<programme start="20251212140000 +0000" stop="20251212145000 +0000" channel="TDM Sport Ch.93.mo"><title>UEFA Europa League / UEFA Conference League 2025/2026 Highlights</title></programme>
<programme start="20251212145000 +0000" stop="20251212150000 +0000" channel="TDM Sport Ch.93.mo"><title>Sport News</title></programme>
<programme start="20251212150000 +0000" stop="20251212170000 +0000" channel="TDM Sport Ch.93.mo"><title>UEFA Europa League 2025/2026 : Celta Vigo vs Bologna (Taped)</title></programme>
<programme start="20251212170000 +0000" stop="20251213015900 +0000" channel="TDM Sport Ch.93.mo"><title>Close</title></programme>
<programme start="20251213015900 +0000" stop="20251213020000 +0000" channel="TDM Sport Ch.93.mo"><title>Open</title></programme>
<programme start="20251213020000 +0000" stop="20251213043000 +0000" channel="TDM Sport Ch.93.mo"><title>2025 US Open Tennis Championships (Edited Version) : Mens Singles Semifinal</title></programme>
</tv>